pudu_ui/__init__.py
pudu_ui/colors.py
pudu_ui/controller.py
pudu_ui/frame.py
pudu_ui/image.py
pudu_ui/label.py
pudu_ui/navigation.py
pudu_ui/progress_bar.py
pudu_ui/screen.py
pudu_ui/slider.py
pudu_ui/widget.py
pudu_ui/app/__init__.py
pudu_ui/buttons/__init__.py
pudu_ui/buttons/button.py
pudu_ui/buttons/image_button.py
pudu_ui/data/__init__.py
pudu_ui/data/array_provider.py
pudu_ui/data/widget_data.py
pudu_ui/layouts/__init__.py
pudu_ui/layouts/grid_layout.py
pudu_ui/layouts/list_layout.py
pudu_ui/primitives/__init__.py
pudu_ui/primitives/quad.py
pudu_ui/shaders/progress_quad.frag
pudu_ui/shaders/quad.vert
pudu_ui/shaders/rounded_quad.frag
pudu_ui/shaders/solid_borders.frag
pudu_ui/shaders/solid_borders.vert
pudu_ui/shaders/solid_colors.frag
pudu_ui/shaders/textured.vert
pudu_ui/shaders/textured_quad.frag
pudu_ui/styles/__init__.py
pudu_ui/styles/buttons.py
pudu_ui/styles/fonts.py
pudu_ui/styles/frames.py
pudu_ui/styles/progress_bars.py
pudu_ui/styles/sliders.py
pudu_ui/utils/__init__.py
pudu_ui-0.1.1.dist-info/licenses/LICENSE
pudu_ui-0.1.1.dist-info/METADATA
pudu_ui-0.1.1.dist-info/WHEEL
pudu_ui-0.1.1.dist-info/top_level.txt
pudu_ui-0.1.1.dist-info/RECORD
