Metadata-Version: 2.4
Name: pudu-ui
Version: 0.1.1
Summary: UI library for Python based in pyglet
Author: Jesus Henriquez
License-Expression: MIT
Project-URL: Homepage, https://github.com/sombra-studio/pudu-ui
Project-URL: Issues, https://github.com/sombra-studio/pudu-ui/issues
Classifier: Programming Language :: Python :: 3
Classifier: Operating System :: OS Independent
Classifier: Topic :: Software Development :: User Interfaces
Requires-Python: >=3.11
License-File: LICENSE
Requires-Dist: pyglet
Dynamic: license-file
